sorted_nearest-0.0.39.dist-info/top_level.txt
sorted_nearest-0.0.39.dist-info/LICENSE.txt
sorted_nearest-0.0.39.dist-info/RECORD
sorted_nearest-0.0.39.dist-info/METADATA
sorted_nearest-0.0.39.dist-info/WHEEL
tests/test_ties.py
tests/conftest.py
examples/test_sorted_nearest.py
examples/test.py
sorted_nearest/version.py
sorted_nearest/__init__.py
sorted_nearest/src/annotate_clusters.pyx
sorted_nearest/src/cluster_by.c
sorted_nearest/src/max_disjoint_intervals.cpython-311-i386-linux-musl.so
sorted_nearest/src/tiles.c
sorted_nearest/src/windows.cpython-311-i386-linux-musl.so
sorted_nearest/src/merge_by.pyx
sorted_nearest/src/windows.pyx
sorted_nearest/src/utarray.h
sorted_nearest/src/introns.c
sorted_nearest/src/merge_by.c
sorted_nearest/src/csorted_nearest.pxd
sorted_nearest/src/k_nearest_ties.c
sorted_nearest/src/k_nearest.cpython-311-i386-linux-musl.so
sorted_nearest/src/sorted_nearest.pyx
sorted_nearest/src/cluster_by.pyx
sorted_nearest/src/sorted_nearest.c
sorted_nearest/src/k_nearest.c
sorted_nearest/src/sorted_nearest.cpython-311-i386-linux-musl.so
sorted_nearest/src/introns.cpython-311-i386-linux-musl.so
sorted_nearest/src/cluster_by.cpython-311-i386-linux-musl.so
sorted_nearest/src/k_nearest_ties.pyx
sorted_nearest/src/annotate_clusters.c
sorted_nearest/src/clusters.c
sorted_nearest/src/tiles.cpython-311-i386-linux-musl.so
sorted_nearest/src/max_disjoint_intervals.c
sorted_nearest/src/max_disjoint_intervals.pyx
sorted_nearest/src/clusters.pyx
sorted_nearest/src/introns.pyx
sorted_nearest/src/tiles.pyx
sorted_nearest/src/k_nearest_ties.cpython-311-i386-linux-musl.so
sorted_nearest/src/k_nearest.pyx
sorted_nearest/src/windows.c
sorted_nearest/src/annotate_clusters.cpython-311-i386-linux-musl.so
sorted_nearest/src/merge_by.cpython-311-i386-linux-musl.so
sorted_nearest/src/clusters.cpython-311-i386-linux-musl.so
sorted_nearest/src/__init__.py
