Metadata-Version: 2.1
Name: sorted_nearest
Version: 0.0.39
Summary: Find nearest intervals.
Author-email: Endre Bakken Stovner <endbak@pm.me>
License: MIT
Project-URL: Homepage, http://github.com/pyranges/sorted_nearest
Keywords: nearest
Classifier: Programming Language :: Python :: 3
Classifier: Development Status :: 4 - Beta
Classifier: Environment :: Other Environment
Classifier: Intended Audience :: Developers
Classifier: Intended Audience :: Science/Research
Classifier: License :: OSI Approved :: MIT License
Classifier: Operating System :: POSIX :: Linux
Classifier: Operating System :: MacOS :: MacOS X
Classifier: Topic :: Scientific/Engineering
Provides-Extra: dev
License-File: LICENSE.txt
